{"TopParent":{"Type":"ControlInfo","Name":"Inventory","Template":{"Id":"http://microsoft.com/appmagic/screen","Version":"1.0","LastModifiedTimestamp":"0","Name":"screen","FirstParty":true,"IsPremiumPcfControl":false,"IsCustomGroupControlTemplate":false,"CustomGroupControlTemplateName":"","IsComponentDefinition":false,"OverridableProperties":{}},"Index":3.0,"PublishOrderIndex":0,"VariantName":"","LayoutName":"","MetaDataIDKey":"","PersistMetaDataIDKey":false,"IsFromScreenLayout":false,"StyleName":"defaultScreenStyle","Parent":"","IsDataControl":false,"AllowAccessToGlobals":true,"IsGroupControl":false,"IsAutoGenerated":false,"Rules":[{"Property":"Fill","Category":"Design","InvariantScript":"White","RuleProviderType":"Unknown"},{"Property":"ImagePosition","Category":"Design","InvariantScript":"ImagePosition.Fit","RuleProviderType":"Unknown"},{"Property":"Height","Category":"Design","InvariantScript":"Max(App.Height, App.MinScreenHeight)","RuleProviderType":"Unknown"},{"Property":"Width","Category":"Design","InvariantScript":"Max(App.Width, App.MinScreenWidth)","RuleProviderType":"Unknown"},{"Property":"Size","Category":"Design","InvariantScript":"1 + CountRows(App.SizeBreakpoints) - CountIf(App.SizeBreakpoints, Value >= Self.Width)","RuleProviderType":"Unknown"},{"Property":"Orientation","Category":"Design","InvariantScript":"If(Self.Width < Self.Height, Layout.Vertical, Layout.Horizontal)","RuleProviderType":"Unknown"},{"Property":"LoadingSpinner","Category":"Design","InvariantScript":"LoadingSpinner.None","RuleProviderType":"Unknown"},{"Property":"LoadingSpinnerColor","Category":"Design","InvariantScript":"RGBA(56, 96, 178, 1)","RuleProviderType":"Unknown"}],"ControlPropertyState":["Fill","ImagePosition","Height","Width","Size","Orientation","LoadingSpinner","LoadingSpinnerColor"],"IsLocked":false,"ControlUniqueId":"13","Children":[{"Type":"ControlInfo","Name":"Rectangle1_1","HasDynamicProperties":false,"Template":{"Id":"http://microsoft.com/appmagic/shapes/rectangle","Version":"2.2.0","LastModifiedTimestamp":"0","Name":"rectangle","FirstParty":true,"IsPremiumPcfControl":false,"IsCustomGroupControlTemplate":false,"CustomGroupControlTemplateName":"","IsComponentDefinition":false,"OverridableProperties":{}},"Index":0.0,"PublishOrderIndex":24,"VariantName":"","LayoutName":"","MetaDataIDKey":"","PersistMetaDataIDKey":false,"IsFromScreenLayout":false,"StyleName":"defaultRectangleStyle","Parent":"Inventory","IsDataControl":false,"AllowAccessToGlobals":true,"IsGroupControl":false,"IsAutoGenerated":false,"Rules":[{"Property":"Fill","Category":"Design","InvariantScript":"RGBA(186, 225, 246, 1)","RuleProviderType":"Unknown"},{"Property":"DisabledFill","Category":"Design","InvariantScript":"Self.Fill","RuleProviderType":"Unknown"},{"Property":"PressedFill","Category":"Design","InvariantScript":"Self.Fill","RuleProviderType":"Unknown"},{"Property":"HoverFill","Category":"Design","InvariantScript":"Self.Fill","RuleProviderType":"Unknown"},{"Property":"BorderColor","Category":"Design","InvariantScript":"RGBA(255, 0, 0, 1)","RuleProviderType":"Unknown"},{"Property":"BorderStyle","Category":"Design","InvariantScript":"BorderStyle.Solid","RuleProviderType":"Unknown"},{"Property":"FocusedBorderColor","Category":"Design","InvariantScript":"Self.BorderColor","RuleProviderType":"Unknown"},{"Property":"DisplayMode","Category":"Design","InvariantScript":"DisplayMode.Edit","RuleProviderType":"Unknown"},{"Property":"X","Category":"Design","InvariantScript":"0","RuleProviderType":"Unknown"},{"Property":"Y","Category":"Design","InvariantScript":"0","RuleProviderType":"Unknown"},{"Property":"Width","Category":"Design","InvariantScript":"1366","RuleProviderType":"Unknown"},{"Property":"Height","Category":"Design","InvariantScript":"100","RuleProviderType":"Unknown"},{"Property":"ZIndex","Category":"Design","InvariantScript":"1","RuleProviderType":"Unknown"},{"Property":"BorderThickness","Category":"Design","InvariantScript":"0","RuleProviderType":"Unknown"},{"Property":"FocusedBorderThickness","Category":"Design","InvariantScript":"2","RuleProviderType":"Unknown"}],"ControlPropertyState":[{"InvariantPropertyName":"Fill","AutoRuleBindingEnabled":false,"AutoRuleBindingString":"","NameMapSourceSchema":"?","IsLockable":false,"AFDDataSourceName":""},"DisabledFill","PressedFill","HoverFill",{"InvariantPropertyName":"BorderColor","AutoRuleBindingEnabled":false,"AutoRuleBindingString":"","NameMapSourceSchema":"?","IsLockable":false,"AFDDataSourceName":""},"BorderStyle","FocusedBorderColor","DisplayMode","X","Y","Width","Height","ZIndex","BorderThickness","FocusedBorderThickness"],"IsLocked":false,"ControlUniqueId":"14","Children":[]},{"Type":"ControlInfo","Name":"Label1_1","HasDynamicProperties":false,"Template":{"Id":"http://microsoft.com/appmagic/label","Version":"2.4.0","LastModifiedTimestamp":"0","Name":"label","FirstParty":true,"IsPremiumPcfControl":false,"IsCustomGroupControlTemplate":false,"CustomGroupControlTemplateName":"","IsComponentDefinition":false,"OverridableProperties":{}},"Index":0.0,"PublishOrderIndex":25,"VariantName":"","LayoutName":"","MetaDataIDKey":"","PersistMetaDataIDKey":false,"IsFromScreenLayout":false,"StyleName":"defaultLabelStyle","Parent":"Inventory","IsDataControl":false,"AllowAccessToGlobals":true,"IsGroupControl":false,"IsAutoGenerated":false,"Rules":[{"Property":"Live","Category":"Data","InvariantScript":"Live.Off","RuleProviderType":"Unknown"},{"Property":"Text","Category":"Data","InvariantScript":"\"Inventory\"","RuleProviderType":"Unknown"},{"Property":"Role","Category":"Data","InvariantScript":"TextRole.Default","RuleProviderType":"Unknown"},{"Property":"Overflow","Category":"Design","InvariantScript":"Overflow.Hidden","RuleProviderType":"Unknown"},{"Property":"Color","Category":"Design","InvariantScript":"RGBA(0, 0, 0, 1)","RuleProviderType":"Unknown"},{"Property":"DisabledColor","Category":"Design","InvariantScript":"RGBA(166, 166, 166, 1)","RuleProviderType":"Unknown"},{"Property":"PressedColor","Category":"Design","InvariantScript":"Self.Color","RuleProviderType":"Unknown"},{"Property":"HoverColor","Category":"Design","InvariantScript":"Self.Color","RuleProviderType":"Unknown"},{"Property":"BorderColor","Category":"Design","InvariantScript":"RGBA(0, 18, 107, 1)","RuleProviderType":"Unknown"},{"Property":"DisabledBorderColor","Category":"Design","InvariantScript":"RGBA(56, 56, 56, 1)","RuleProviderType":"Unknown"},{"Property":"PressedBorderColor","Category":"Design","InvariantScript":"Self.BorderColor","RuleProviderType":"Unknown"},{"Property":"HoverBorderColor","Category":"Design","InvariantScript":"Self.BorderColor","RuleProviderType":"Unknown"},{"Property":"BorderStyle","Category":"Design","InvariantScript":"BorderStyle.Solid","RuleProviderType":"Unknown"},{"Property":"FocusedBorderColor","Category":"Design","InvariantScript":"Self.BorderColor","RuleProviderType":"Unknown"},{"Property":"Fill","Category":"Design","InvariantScript":"RGBA(0, 0, 0, 0)","RuleProviderType":"Unknown"},{"Property":"DisabledFill","Category":"Design","InvariantScript":"RGBA(0, 0, 0, 0)","RuleProviderType":"Unknown"},{"Property":"PressedFill","Category":"Design","InvariantScript":"Self.Fill","RuleProviderType":"Unknown"},{"Property":"HoverFill","Category":"Design","InvariantScript":"Self.Fill","RuleProviderType":"Unknown"},{"Property":"Font","Category":"Design","InvariantScript":"Font.Arial","RuleProviderType":"Unknown"},{"Property":"FontWeight","Category":"Design","InvariantScript":"FontWeight.Normal","RuleProviderType":"Unknown"},{"Property":"Align","Category":"Design","InvariantScript":"Align.Center","RuleProviderType":"Unknown"},{"Property":"VerticalAlign","Category":"Design","InvariantScript":"VerticalAlign.Middle","RuleProviderType":"Unknown"},{"Property":"X","Category":"Design","InvariantScript":"460","RuleProviderType":"Unknown"},{"Property":"Y","Category":"Design","InvariantScript":"15","RuleProviderType":"Unknown"},{"Property":"Width","Category":"Design","InvariantScript":"445","RuleProviderType":"Unknown"},{"Property":"Height","Category":"Design","InvariantScript":"70","RuleProviderType":"Unknown"},{"Property":"DisplayMode","Category":"Design","InvariantScript":"DisplayMode.Edit","RuleProviderType":"Unknown"},{"Property":"ZIndex","Category":"Design","InvariantScript":"3","RuleProviderType":"Unknown"},{"Property":"LineHeight","Category":"Design","InvariantScript":"1.2","RuleProviderType":"Unknown"},{"Property":"BorderThickness","Category":"Design","InvariantScript":"0","RuleProviderType":"Unknown"},{"Property":"FocusedBorderThickness","Category":"Design","InvariantScript":"0","RuleProviderType":"Unknown"},{"Property":"Size","Category":"Design","InvariantScript":"25","RuleProviderType":"Unknown"},{"Property":"Italic","Category":"Design","InvariantScript":"false","RuleProviderType":"Unknown"},{"Property":"Underline","Category":"Design","InvariantScript":"false","RuleProviderType":"Unknown"},{"Property":"Strikethrough","Category":"Design","InvariantScript":"false","RuleProviderType":"Unknown"},{"Property":"PaddingTop","Category":"Design","InvariantScript":"5","RuleProviderType":"Unknown"},{"Property":"PaddingRight","Category":"Design","InvariantScript":"5","RuleProviderType":"Unknown"},{"Property":"PaddingBottom","Category":"Design","InvariantScript":"5","RuleProviderType":"Unknown"},{"Property":"PaddingLeft","Category":"Design","InvariantScript":"5","RuleProviderType":"Unknown"}],"ControlPropertyState":["Live",{"InvariantPropertyName":"Overflow","AutoRuleBindingEnabled":false,"AutoRuleBindingString":"","NameMapSourceSchema":"?","IsLockable":false,"AFDDataSourceName":""},{"InvariantPropertyName":"Text","AutoRuleBindingEnabled":false,"AutoRuleBindingString":"\"Text\"","NameMapSourceSchema":"?","IsLockable":false,"AFDDataSourceName":""},"Role","Color","DisabledColor","PressedColor","HoverColor","BorderColor","DisabledBorderColor","PressedBorderColor","HoverBorderColor","BorderStyle","FocusedBorderColor","Fill","DisabledFill","PressedFill","HoverFill",{"InvariantPropertyName":"Font","AutoRuleBindingEnabled":false,"AutoRuleBindingString":"","NameMapSourceSchema":"?","IsLockable":false,"AFDDataSourceName":""},"FontWeight",{"InvariantPropertyName":"Align","AutoRuleBindingEnabled":false,"AutoRuleBindingString":"","NameMapSourceSchema":"?","IsLockable":false,"AFDDataSourceName":""},"VerticalAlign","X","Y","Width","Height","DisplayMode","ZIndex","LineHeight","BorderThickness","FocusedBorderThickness",{"InvariantPropertyName":"Size","AutoRuleBindingEnabled":false,"AutoRuleBindingString":"","NameMapSourceSchema":"?","IsLockable":false,"AFDDataSourceName":""},"Italic","Underline","Strikethrough","PaddingTop","PaddingRight","PaddingBottom","PaddingLeft"],"IsLocked":false,"ControlUniqueId":"15","Children":[]},{"Type":"ControlInfo","Name":"Icon1_1","HasDynamicProperties":false,"Template":{"Id":"http://microsoft.com/appmagic/icon","Version":"2.4.0","LastModifiedTimestamp":"0","Name":"icon","FirstParty":true,"IsPremiumPcfControl":false,"IsCustomGroupControlTemplate":false,"CustomGroupControlTemplateName":"","IsComponentDefinition":false,"OverridableProperties":{}},"Index":0.0,"PublishOrderIndex":26,"VariantName":"People","LayoutName":"","MetaDataIDKey":"","PersistMetaDataIDKey":false,"IsFromScreenLayout":false,"StyleName":"defaultIconStyle","Parent":"Inventory","IsDataControl":false,"AllowAccessToGlobals":true,"IsGroupControl":false,"IsAutoGenerated":false,"Rules":[{"Property":"Icon","Category":"Design","InvariantScript":"Icon.People","RuleProviderType":"Unknown"},{"Property":"Color","Category":"Design","InvariantScript":"RGBA(255, 255, 255, 1)","RuleProviderType":"Unknown"},{"Property":"DisabledColor","Category":"Design","InvariantScript":"RGBA(244, 244, 244, 1)","RuleProviderType":"Unknown"},{"Property":"PressedColor","Category":"Design","InvariantScript":"ColorFade(Self.Color, -20%)","RuleProviderType":"Unknown"},{"Property":"HoverColor","Category":"Design","InvariantScript":"ColorFade(Self.Color, 20%)","RuleProviderType":"Unknown"},{"Property":"Fill","Category":"Design","InvariantScript":"RGBA(0, 0, 0, 0)","RuleProviderType":"Unknown"},{"Property":"DisabledFill","Category":"Design","InvariantScript":"Self.Fill","RuleProviderType":"Unknown"},{"Property":"PressedFill","Category":"Design","InvariantScript":"Self.Fill","RuleProviderType":"Unknown"},{"Property":"HoverFill","Category":"Design","InvariantScript":"Self.Fill","RuleProviderType":"Unknown"},{"Property":"DisplayMode","Category":"Design","InvariantScript":"DisplayMode.Edit","RuleProviderType":"Unknown"},{"Property":"X","Category":"Design","InvariantScript":"41","RuleProviderType":"Unknown"},{"Property":"Y","Category":"Design","InvariantScript":"18","RuleProviderType":"Unknown"},{"Property":"Width","Category":"Design","InvariantScript":"64","RuleProviderType":"Unknown"},{"Property":"Height","Category":"Design","InvariantScript":"64","RuleProviderType":"Unknown"},{"Property":"BorderStyle","Category":"Design","InvariantScript":"BorderStyle.Solid","RuleProviderType":"Unknown"},{"Property":"BorderColor","Category":"Design","InvariantScript":"RGBA(0, 18, 107, 1)","RuleProviderType":"Unknown"},{"Property":"DisabledBorderColor","Category":"Design","InvariantScript":"RGBA(166, 166, 166, 1)","RuleProviderType":"Unknown"},{"Property":"PressedBorderColor","Category":"Design","InvariantScript":"ColorFade(Self.BorderColor, -20%)","RuleProviderType":"Unknown"},{"Property":"HoverBorderColor","Category":"Design","InvariantScript":"ColorFade(Self.BorderColor, 20%)","RuleProviderType":"Unknown"},{"Property":"FocusedBorderColor","Category":"Design","InvariantScript":"Self.BorderColor","RuleProviderType":"Unknown"},{"Property":"ZIndex","Category":"Design","InvariantScript":"2","RuleProviderType":"Unknown"},{"Property":"BorderThickness","Category":"Design","InvariantScript":"0","RuleProviderType":"Unknown"},{"Property":"FocusedBorderThickness","Category":"Design","InvariantScript":"2","RuleProviderType":"Unknown"}],"ControlPropertyState":["Icon",{"InvariantPropertyName":"Color","AutoRuleBindingEnabled":false,"AutoRuleBindingString":"","NameMapSourceSchema":"?","IsLockable":false,"AFDDataSourceName":""},"DisabledColor","PressedColor","HoverColor","Fill","DisabledFill","PressedFill","HoverFill","DisplayMode","X","Y","Width","Height","BorderStyle","BorderColor","DisabledBorderColor","PressedBorderColor","HoverBorderColor","FocusedBorderColor","ZIndex","BorderThickness","FocusedBorderThickness"],"IsLocked":false,"ControlUniqueId":"16","Children":[]},{"Type":"ControlInfo","Name":"DataTable4","HasDynamicProperties":false,"Template":{"Id":"http://microsoft.com/appmagic/dataTable","Version":"1.0.2","LastModifiedTimestamp":"0","Name":"dataTable","FirstParty":true,"IsPremiumPcfControl":false,"IsCustomGroupControlTemplate":false,"CustomGroupControlTemplateName":"","IsComponentDefinition":false,"OverridableProperties":{}},"Index":0.0,"PublishOrderIndex":27,"VariantName":"datatable","LayoutName":"","MetaDataIDKey":"","PersistMetaDataIDKey":false,"IsFromScreenLayout":false,"StyleName":"defaultDataTableStyle","Parent":"Inventory","IsDataControl":false,"AllowAccessToGlobals":true,"IsGroupControl":false,"IsAutoGenerated":false,"Rules":[{"Property":"Items","Category":"Data","InvariantScript":"Table1_4","RuleProviderType":"Unknown"},{"Property":"Fill","Category":"Design","InvariantScript":"RGBA(0, 0, 0, 0)","RuleProviderType":"Unknown"},{"Property":"Color","Category":"Design","InvariantScript":"RGBA(0, 0, 0, 1)","RuleProviderType":"Unknown"},{"Property":"DisabledColor","Category":"Design","InvariantScript":"RGBA(166, 166, 166, 1)","RuleProviderType":"Unknown"},{"Property":"BorderColor","Category":"Design","InvariantScript":"RGBA(204, 231, 246, 1)","RuleProviderType":"Unknown"},{"Property":"BorderStyle","Category":"Design","InvariantScript":"BorderStyle.Solid","RuleProviderType":"Unknown"},{"Property":"Font","Category":"Design","InvariantScript":"Font.'Open Sans'","RuleProviderType":"Unknown"},{"Property":"FontWeight","Category":"Design","InvariantScript":"FontWeight.Normal","RuleProviderType":"Unknown"},{"Property":"X","Category":"Design","InvariantScript":"196","RuleProviderType":"Unknown"},{"Property":"Y","Category":"Design","InvariantScript":"123","RuleProviderType":"Unknown"},{"Property":"Width","Category":"Design","InvariantScript":"972","RuleProviderType":"Unknown"},{"Property":"Height","Category":"Design","InvariantScript":"500","RuleProviderType":"Unknown"},{"Property":"DisplayMode","Category":"Design","InvariantScript":"DisplayMode.Edit","RuleProviderType":"Unknown"},{"Property":"ZIndex","Category":"Design","InvariantScript":"7","RuleProviderType":"Unknown"},{"Property":"LinkColor","Category":"Design","InvariantScript":"RGBA(0, 134, 208, 1)","RuleProviderType":"Unknown"},{"Property":"PrimaryColor1","Category":"Design","InvariantScript":"RGBA(56, 96, 178, 1)","RuleProviderType":"Unknown"},{"Property":"PrimaryColor2","Category":"Design","InvariantScript":"RGBA(0, 18, 107, 1)","RuleProviderType":"Unknown"},{"Property":"PrimaryColor3","Category":"Design","InvariantScript":"RGBA(186, 202, 226, 1)","RuleProviderType":"Unknown"},{"Property":"SelectedFill","Category":"Design","InvariantScript":"RGBA(56, 96, 178, .2)","RuleProviderType":"Unknown"},{"Property":"SelectedColor","Category":"Design","InvariantScript":"RGBA(0, 0, 0, 1)","RuleProviderType":"Unknown"},{"Property":"HoverFill","Category":"Design","InvariantScript":"RGBA(186, 202, 226, .2)","RuleProviderType":"Unknown"},{"Property":"HoverColor","Category":"Design","InvariantScript":"RGBA(0, 0, 0, 1)","RuleProviderType":"Unknown"},{"Property":"InputFill","Category":"Design","InvariantScript":"RGBA(255, 255, 255, 1)","RuleProviderType":"Unknown"},{"Property":"InvertedColor","Category":"Design","InvariantScript":"RGBA(255, 255, 255, 1)","RuleProviderType":"Unknown"},{"Property":"HeadingFont","Category":"Design","InvariantScript":"Font.'Open Sans'","RuleProviderType":"Unknown"},{"Property":"HeadingSize","Category":"Design","InvariantScript":"13","RuleProviderType":"Unknown"},{"Property":"HeadingFontWeight","Category":"Design","InvariantScript":"FontWeight.Normal","RuleProviderType":"Unknown"},{"Property":"HeadingFill","Category":"Design","InvariantScript":"RGBA(56, 96, 178, 1)","RuleProviderType":"Unknown"},{"Property":"HeadingColor","Category":"Design","InvariantScript":"RGBA(255, 255, 255, 1)","RuleProviderType":"Unknown"},{"Property":"Size","Category":"Design","InvariantScript":"13","RuleProviderType":"Unknown"},{"Property":"BorderThickness","Category":"Design","InvariantScript":"4","RuleProviderType":"Unknown"}],"ControlPropertyState":["Fill","Color","DisabledColor",{"InvariantPropertyName":"BorderColor","AutoRuleBindingEnabled":false,"AutoRuleBindingString":"","NameMapSourceSchema":"?","IsLockable":false,"AFDDataSourceName":""},"BorderStyle","Font","FontWeight","X","Y","Width","Height","DisplayMode","ZIndex","LinkColor","PrimaryColor1","PrimaryColor2","PrimaryColor3","SelectedFill","SelectedColor","HoverFill","HoverColor","InputFill","InvertedColor","HeadingFont","HeadingSize","HeadingFontWeight","HeadingFill","HeadingColor","Size",{"InvariantPropertyName":"Items","AutoRuleBindingEnabled":false,"AutoRuleBindingString":"","NameMapSourceSchema":"?","IsLockable":false,"AFDDataSourceName":""},{"InvariantPropertyName":"BorderThickness","AutoRuleBindingEnabled":false,"AutoRuleBindingString":"","NameMapSourceSchema":"?","IsLockable":false,"AFDDataSourceName":""}],"IsLocked":false,"ControlUniqueId":"17","Children":[{"Type":"ControlInfo","Name":"#_Column2","HasDynamicProperties":false,"Template":{"Id":"http://microsoft.com/appmagic/dataTableColumn","Version":"1.0.1","LastModifiedTimestamp":"0","Name":"dataTableColumn","FirstParty":true,"IsPremiumPcfControl":false,"IsCustomGroupControlTemplate":false,"CustomGroupControlTemplateName":"","IsComponentDefinition":false,"OverridableProperties":{}},"Index":0.0,"PublishOrderIndex":28,"VariantName":"textualColumn","LayoutName":"","MetaDataIDKey":"","PersistMetaDataIDKey":false,"IsFromScreenLayout":false,"StyleName":"","Parent":"DataTable4","IsDataControl":false,"AllowAccessToGlobals":true,"IsGroupControl":false,"IsAutoGenerated":false,"Rules":[{"Property":"FieldName","Category":"Data","InvariantScript":"\"#\"","RuleProviderType":"Unknown"},{"Property":"Order","Category":"Data","InvariantScript":"1","RuleProviderType":"Unknown"},{"Property":"FieldVariantName","Category":"Data","InvariantScript":"\"textualColumn\"","RuleProviderType":"Unknown"},{"Property":"FieldDisplayName","Category":"Data","InvariantScript":"\"#\"","RuleProviderType":"Unknown"},{"Property":"Text","Category":"Data","InvariantScript":"ThisItem.'#'","RuleProviderType":"Unknown"},{"Property":"LayoutHeight","Category":"Design","InvariantScript":"Parent.Height","RuleProviderType":"Unknown"},{"Property":"X","Category":"Design","InvariantScript":"0","RuleProviderType":"Unknown"},{"Property":"Y","Category":"Design","InvariantScript":"0","RuleProviderType":"Unknown"},{"Property":"Width","Category":"Design","InvariantScript":"100","RuleProviderType":"Unknown"},{"Property":"Height","Category":"Design","InvariantScript":"Parent.Height","RuleProviderType":"Unknown"},{"Property":"DisplayMode","Category":"Design","InvariantScript":"DisplayMode.Edit","RuleProviderType":"Unknown"},{"Property":"ZIndex","Category":"Design","InvariantScript":"1","RuleProviderType":"Unknown"}],"ControlPropertyState":["FieldName","Order","FieldVariantName","FieldDisplayName","LayoutHeight","X","Y","Width","Height","DisplayMode","ZIndex","Text"],"IsLocked":true,"ControlUniqueId":"18","Children":[]},{"Type":"ControlInfo","Name":"Nme_Column2","HasDynamicProperties":false,"Template":{"Id":"http://microsoft.com/appmagic/dataTableColumn","Version":"1.0.1","LastModifiedTimestamp":"0","Name":"dataTableColumn","FirstParty":true,"IsPremiumPcfControl":false,"IsCustomGroupControlTemplate":false,"CustomGroupControlTemplateName":"","IsComponentDefinition":false,"OverridableProperties":{}},"Index":0.0,"PublishOrderIndex":29,"VariantName":"textualColumn","LayoutName":"","MetaDataIDKey":"","PersistMetaDataIDKey":false,"IsFromScreenLayout":false,"StyleName":"","Parent":"DataTable4","IsDataControl":false,"AllowAccessToGlobals":true,"IsGroupControl":false,"IsAutoGenerated":false,"Rules":[{"Property":"FieldName","Category":"Data","InvariantScript":"\"Nme\"","RuleProviderType":"Unknown"},{"Property":"Order","Category":"Data","InvariantScript":"2","RuleProviderType":"Unknown"},{"Property":"FieldVariantName","Category":"Data","InvariantScript":"\"textualColumn\"","RuleProviderType":"Unknown"},{"Property":"FieldDisplayName","Category":"Data","InvariantScript":"\"Nme\"","RuleProviderType":"Unknown"},{"Property":"Text","Category":"Data","InvariantScript":"ThisItem.Nme","RuleProviderType":"Unknown"},{"Property":"LayoutHeight","Category":"Design","InvariantScript":"Parent.Height","RuleProviderType":"Unknown"},{"Property":"X","Category":"Design","InvariantScript":"0","RuleProviderType":"Unknown"},{"Property":"Y","Category":"Design","InvariantScript":"0","RuleProviderType":"Unknown"},{"Property":"Width","Category":"Design","InvariantScript":"100","RuleProviderType":"Unknown"},{"Property":"Height","Category":"Design","InvariantScript":"Parent.Height","RuleProviderType":"Unknown"},{"Property":"DisplayMode","Category":"Design","InvariantScript":"DisplayMode.Edit","RuleProviderType":"Unknown"},{"Property":"ZIndex","Category":"Design","InvariantScript":"2","RuleProviderType":"Unknown"}],"ControlPropertyState":["FieldName","Order","FieldVariantName","FieldDisplayName","LayoutHeight","X","Y","Width","Height","DisplayMode","ZIndex","Text"],"IsLocked":true,"ControlUniqueId":"19","Children":[]},{"Type":"ControlInfo","Name":"Type_Column2","HasDynamicProperties":false,"Template":{"Id":"http://microsoft.com/appmagic/dataTableColumn","Version":"1.0.1","LastModifiedTimestamp":"0","Name":"dataTableColumn","FirstParty":true,"IsPremiumPcfControl":false,"IsCustomGroupControlTemplate":false,"CustomGroupControlTemplateName":"","IsComponentDefinition":false,"OverridableProperties":{}},"Index":0.0,"PublishOrderIndex":30,"VariantName":"textualColumn","LayoutName":"","MetaDataIDKey":"","PersistMetaDataIDKey":false,"IsFromScreenLayout":false,"StyleName":"","Parent":"DataTable4","IsDataControl":false,"AllowAccessToGlobals":true,"IsGroupControl":false,"IsAutoGenerated":false,"Rules":[{"Property":"FieldName","Category":"Data","InvariantScript":"\"Type\"","RuleProviderType":"Unknown"},{"Property":"Order","Category":"Data","InvariantScript":"3","RuleProviderType":"Unknown"},{"Property":"FieldVariantName","Category":"Data","InvariantScript":"\"textualColumn\"","RuleProviderType":"Unknown"},{"Property":"FieldDisplayName","Category":"Data","InvariantScript":"\"Type\"","RuleProviderType":"Unknown"},{"Property":"Text","Category":"Data","InvariantScript":"ThisItem.Type","RuleProviderType":"Unknown"},{"Property":"LayoutHeight","Category":"Design","InvariantScript":"Parent.Height","RuleProviderType":"Unknown"},{"Property":"X","Category":"Design","InvariantScript":"0","RuleProviderType":"Unknown"},{"Property":"Y","Category":"Design","InvariantScript":"0","RuleProviderType":"Unknown"},{"Property":"Width","Category":"Design","InvariantScript":"100","RuleProviderType":"Unknown"},{"Property":"Height","Category":"Design","InvariantScript":"Parent.Height","RuleProviderType":"Unknown"},{"Property":"DisplayMode","Category":"Design","InvariantScript":"DisplayMode.Edit","RuleProviderType":"Unknown"},{"Property":"ZIndex","Category":"Design","InvariantScript":"3","RuleProviderType":"Unknown"}],"ControlPropertyState":["FieldName","Order","FieldVariantName","FieldDisplayName","LayoutHeight","X","Y","Width","Height","DisplayMode","ZIndex","Text"],"IsLocked":true,"ControlUniqueId":"20","Children":[]},{"Type":"ControlInfo","Name":"Date_Column2","HasDynamicProperties":false,"Template":{"Id":"http://microsoft.com/appmagic/dataTableColumn","Version":"1.0.1","LastModifiedTimestamp":"0","Name":"dataTableColumn","FirstParty":true,"IsPremiumPcfControl":false,"IsCustomGroupControlTemplate":false,"CustomGroupControlTemplateName":"","IsComponentDefinition":false,"OverridableProperties":{}},"Index":0.0,"PublishOrderIndex":31,"VariantName":"textualColumn","LayoutName":"","MetaDataIDKey":"","PersistMetaDataIDKey":false,"IsFromScreenLayout":false,"StyleName":"","Parent":"DataTable4","IsDataControl":false,"AllowAccessToGlobals":true,"IsGroupControl":false,"IsAutoGenerated":false,"Rules":[{"Property":"FieldName","Category":"Data","InvariantScript":"\"Date\"","RuleProviderType":"Unknown"},{"Property":"Order","Category":"Data","InvariantScript":"4","RuleProviderType":"Unknown"},{"Property":"FieldVariantName","Category":"Data","InvariantScript":"\"textualColumn\"","RuleProviderType":"Unknown"},{"Property":"FieldDisplayName","Category":"Data","InvariantScript":"\"Date\"","RuleProviderType":"Unknown"},{"Property":"Text","Category":"Data","InvariantScript":"ThisItem.Date","RuleProviderType":"Unknown"},{"Property":"LayoutHeight","Category":"Design","InvariantScript":"Parent.Height","RuleProviderType":"Unknown"},{"Property":"X","Category":"Design","InvariantScript":"0","RuleProviderType":"Unknown"},{"Property":"Y","Category":"Design","InvariantScript":"0","RuleProviderType":"Unknown"},{"Property":"Width","Category":"Design","InvariantScript":"100","RuleProviderType":"Unknown"},{"Property":"Height","Category":"Design","InvariantScript":"Parent.Height","RuleProviderType":"Unknown"},{"Property":"DisplayMode","Category":"Design","InvariantScript":"DisplayMode.Edit","RuleProviderType":"Unknown"},{"Property":"ZIndex","Category":"Design","InvariantScript":"4","RuleProviderType":"Unknown"}],"ControlPropertyState":["FieldName","Order","FieldVariantName","FieldDisplayName","LayoutHeight","X","Y","Width","Height","DisplayMode","ZIndex","Text"],"IsLocked":true,"ControlUniqueId":"21","Children":[]},{"Type":"ControlInfo","Name":"Sold_Column2","HasDynamicProperties":false,"Template":{"Id":"http://microsoft.com/appmagic/dataTableColumn","Version":"1.0.1","LastModifiedTimestamp":"0","Name":"dataTableColumn","FirstParty":true,"IsPremiumPcfControl":false,"IsCustomGroupControlTemplate":false,"CustomGroupControlTemplateName":"","IsComponentDefinition":false,"OverridableProperties":{}},"Index":0.0,"PublishOrderIndex":32,"VariantName":"textualColumn","LayoutName":"","MetaDataIDKey":"","PersistMetaDataIDKey":false,"IsFromScreenLayout":false,"StyleName":"","Parent":"DataTable4","IsDataControl":false,"AllowAccessToGlobals":true,"IsGroupControl":false,"IsAutoGenerated":false,"Rules":[{"Property":"FieldName","Category":"Data","InvariantScript":"\"Sold\"","RuleProviderType":"Unknown"},{"Property":"Order","Category":"Data","InvariantScript":"6","RuleProviderType":"Unknown"},{"Property":"FieldVariantName","Category":"Data","InvariantScript":"\"textualColumn\"","RuleProviderType":"Unknown"},{"Property":"FieldDisplayName","Category":"Data","InvariantScript":"\"Sold\"","RuleProviderType":"Unknown"},{"Property":"Text","Category":"Data","InvariantScript":"ThisItem.Sold","RuleProviderType":"Unknown"},{"Property":"AutoWidth","Category":"Data","InvariantScript":"false","RuleProviderType":"Unknown"},{"Property":"LayoutHeight","Category":"Design","InvariantScript":"Parent.Height","RuleProviderType":"Unknown"},{"Property":"X","Category":"Design","InvariantScript":"0","RuleProviderType":"Unknown"},{"Property":"Y","Category":"Design","InvariantScript":"0","RuleProviderType":"Unknown"},{"Property":"Width","Category":"Design","InvariantScript":"132","RuleProviderType":"Unknown"},{"Property":"Height","Category":"Design","InvariantScript":"Parent.Height","RuleProviderType":"Unknown"},{"Property":"DisplayMode","Category":"Design","InvariantScript":"DisplayMode.Edit","RuleProviderType":"Unknown"},{"Property":"ZIndex","Category":"Design","InvariantScript":"6","RuleProviderType":"Unknown"}],"ControlPropertyState":["FieldName","Order","FieldVariantName","FieldDisplayName","LayoutHeight","X","Y","Width","Height","DisplayMode","ZIndex","Text","AutoWidth"],"IsLocked":true,"ControlUniqueId":"23","Children":[]},{"Type":"ControlInfo","Name":"Stock_Column2","HasDynamicProperties":false,"Template":{"Id":"http://microsoft.com/appmagic/dataTableColumn","Version":"1.0.1","LastModifiedTimestamp":"0","Name":"dataTableColumn","FirstParty":true,"IsPremiumPcfControl":false,"IsCustomGroupControlTemplate":false,"CustomGroupControlTemplateName":"","IsComponentDefinition":false,"OverridableProperties":{}},"Index":0.0,"PublishOrderIndex":33,"VariantName":"textualColumn","LayoutName":"","MetaDataIDKey":"","PersistMetaDataIDKey":false,"IsFromScreenLayout":false,"StyleName":"","Parent":"DataTable4","IsDataControl":false,"AllowAccessToGlobals":true,"IsGroupControl":false,"IsAutoGenerated":false,"Rules":[{"Property":"FieldName","Category":"Data","InvariantScript":"\"Stock\"","RuleProviderType":"Unknown"},{"Property":"Order","Category":"Data","InvariantScript":"5","RuleProviderType":"Unknown"},{"Property":"FieldVariantName","Category":"Data","InvariantScript":"\"textualColumn\"","RuleProviderType":"Unknown"},{"Property":"FieldDisplayName","Category":"Data","InvariantScript":"\"Stock\"","RuleProviderType":"Unknown"},{"Property":"Text","Category":"Data","InvariantScript":"ThisItem.Stock","RuleProviderType":"Unknown"},{"Property":"AutoWidth","Category":"Data","InvariantScript":"false","RuleProviderType":"Unknown"},{"Property":"LayoutHeight","Category":"Design","InvariantScript":"Parent.Height","RuleProviderType":"Unknown"},{"Property":"X","Category":"Design","InvariantScript":"643","RuleProviderType":"Unknown"},{"Property":"Y","Category":"Design","InvariantScript":"0","RuleProviderType":"Unknown"},{"Property":"Width","Category":"Design","InvariantScript":"157","RuleProviderType":"Unknown"},{"Property":"Height","Category":"Design","InvariantScript":"500","RuleProviderType":"Unknown"},{"Property":"DisplayMode","Category":"Design","InvariantScript":"DisplayMode.Edit","RuleProviderType":"Unknown"},{"Property":"ZIndex","Category":"Design","InvariantScript":"5","RuleProviderType":"Unknown"}],"ControlPropertyState":["FieldName","Order","FieldVariantName","FieldDisplayName","LayoutHeight","X","Y","Width","Height","DisplayMode","ZIndex","Text","AutoWidth"],"IsLocked":true,"ControlUniqueId":"22","Children":[]}]},{"Type":"ControlInfo","Name":"Button2_2","HasDynamicProperties":false,"Template":{"Id":"http://microsoft.com/appmagic/button","Version":"2.1.0","LastModifiedTimestamp":"0","Name":"button","FirstParty":true,"IsPremiumPcfControl":false,"IsCustomGroupControlTemplate":false,"CustomGroupControlTemplateName":"","IsComponentDefinition":false,"OverridableProperties":{}},"Index":0.0,"PublishOrderIndex":34,"VariantName":"","LayoutName":"","MetaDataIDKey":"","PersistMetaDataIDKey":false,"IsFromScreenLayout":false,"StyleName":"defaultButtonStyle","Parent":"Inventory","IsDataControl":false,"AllowAccessToGlobals":true,"IsGroupControl":false,"IsAutoGenerated":false,"Rules":[{"Property":"Text","Category":"Data","InvariantScript":"\"Back\"","RuleProviderType":"Unknown"},{"Property":"BorderColor","Category":"Design","InvariantScript":"ColorFade(Self.Fill, -15%)","RuleProviderType":"Unknown"},{"Property":"DisabledBorderColor","Category":"Design","InvariantScript":"RGBA(166, 166, 166, 1)","RuleProviderType":"Unknown"},{"Property":"PressedBorderColor","Category":"Design","InvariantScript":"Self.Fill","RuleProviderType":"Unknown"},{"Property":"HoverBorderColor","Category":"Design","InvariantScript":"ColorFade(Self.BorderColor, 20%)","RuleProviderType":"Unknown"},{"Property":"BorderStyle","Category":"Design","InvariantScript":"BorderStyle.Solid","RuleProviderType":"Unknown"},{"Property":"FocusedBorderColor","Category":"Design","InvariantScript":"Self.BorderColor","RuleProviderType":"Unknown"},{"Property":"Color","Category":"Design","InvariantScript":"RGBA(255, 255, 255, 1)","RuleProviderType":"Unknown"},{"Property":"DisabledColor","Category":"Design","InvariantScript":"RGBA(166, 166, 166, 1)","RuleProviderType":"Unknown"},{"Property":"PressedColor","Category":"Design","InvariantScript":"Self.Fill","RuleProviderType":"Unknown"},{"Property":"HoverColor","Category":"Design","InvariantScript":"RGBA(255, 255, 255, 1)","RuleProviderType":"Unknown"},{"Property":"DisplayMode","Category":"Design","InvariantScript":"DisplayMode.Edit","RuleProviderType":"Unknown"},{"Property":"Fill","Category":"Design","InvariantScript":"RGBA(56, 96, 178, 1)","RuleProviderType":"Unknown"},{"Property":"DisabledFill","Category":"Design","InvariantScript":"RGBA(244, 244, 244, 1)","RuleProviderType":"Unknown"},{"Property":"PressedFill","Category":"Design","InvariantScript":"Self.Color","RuleProviderType":"Unknown"},{"Property":"HoverFill","Category":"Design","InvariantScript":"ColorFade(RGBA(56, 96, 178, 1), -20%)","RuleProviderType":"Unknown"},{"Property":"Font","Category":"Design","InvariantScript":"Font.'Open Sans'","RuleProviderType":"Unknown"},{"Property":"FontWeight","Category":"Design","InvariantScript":"FontWeight.Semibold","RuleProviderType":"Unknown"},{"Property":"Align","Category":"Design","InvariantScript":"Align.Center","RuleProviderType":"Unknown"},{"Property":"VerticalAlign","Category":"Design","InvariantScript":"VerticalAlign.Middle","RuleProviderType":"Unknown"},{"Property":"X","Category":"Design","InvariantScript":"272","RuleProviderType":"Unknown"},{"Property":"Y","Category":"Design","InvariantScript":"665","RuleProviderType":"Unknown"},{"Property":"Width","Category":"Design","InvariantScript":"188","RuleProviderType":"Unknown"},{"Property":"Height","Category":"Design","InvariantScript":"63","RuleProviderType":"Unknown"},{"Property":"ZIndex","Category":"Design","InvariantScript":"6","RuleProviderType":"Unknown"},{"Property":"RadiusTopLeft","Category":"Design","InvariantScript":"10","RuleProviderType":"Unknown"},{"Property":"RadiusTopRight","Category":"Design","InvariantScript":"10","RuleProviderType":"Unknown"},{"Property":"RadiusBottomLeft","Category":"Design","InvariantScript":"10","RuleProviderType":"Unknown"},{"Property":"RadiusBottomRight","Category":"Design","InvariantScript":"10","RuleProviderType":"Unknown"},{"Property":"BorderThickness","Category":"Design","InvariantScript":"2","RuleProviderType":"Unknown"},{"Property":"FocusedBorderThickness","Category":"Design","InvariantScript":"4","RuleProviderType":"Unknown"},{"Property":"Size","Category":"Design","InvariantScript":"15","RuleProviderType":"Unknown"},{"Property":"Italic","Category":"Design","InvariantScript":"false","RuleProviderType":"Unknown"},{"Property":"Underline","Category":"Design","InvariantScript":"false","RuleProviderType":"Unknown"},{"Property":"Strikethrough","Category":"Design","InvariantScript":"false","RuleProviderType":"Unknown"},{"Property":"OnSelect","Category":"Behavior","InvariantScript":"Navigate(Home, ScreenTransition.Fade)","RuleProviderType":"Unknown"}],"ControlPropertyState":[{"InvariantPropertyName":"Text","AutoRuleBindingEnabled":false,"AutoRuleBindingString":"\"Button\"","NameMapSourceSchema":"?","IsLockable":false,"AFDDataSourceName":""},"BorderColor","DisabledBorderColor","PressedBorderColor","HoverBorderColor","BorderStyle","FocusedBorderColor","Color","DisabledColor","PressedColor","HoverColor","DisplayMode","Fill","DisabledFill","PressedFill","HoverFill","Font","FontWeight","Align","VerticalAlign","X","Y","Width","Height","ZIndex","RadiusTopLeft","RadiusTopRight","RadiusBottomLeft","RadiusBottomRight","BorderThickness","FocusedBorderThickness","Size","Italic","Underline","Strikethrough",{"InvariantPropertyName":"OnSelect","AutoRuleBindingEnabled":false,"AutoRuleBindingString":"false","NameMapSourceSchema":"?","IsLockable":false,"AFDDataSourceName":""}],"IsLocked":false,"ControlUniqueId":"24","Children":[]},{"Type":"ControlInfo","Name":"Button1_2","HasDynamicProperties":false,"Template":{"Id":"http://microsoft.com/appmagic/button","Version":"2.1.0","LastModifiedTimestamp":"0","Name":"button","FirstParty":true,"IsPremiumPcfControl":false,"IsCustomGroupControlTemplate":false,"CustomGroupControlTemplateName":"","IsComponentDefinition":false,"OverridableProperties":{}},"Index":0.0,"PublishOrderIndex":35,"VariantName":"","LayoutName":"","MetaDataIDKey":"","PersistMetaDataIDKey":false,"IsFromScreenLayout":false,"StyleName":"defaultButtonStyle","Parent":"Inventory","IsDataControl":false,"AllowAccessToGlobals":true,"IsGroupControl":false,"IsAutoGenerated":false,"Rules":[{"Property":"Text","Category":"Data","InvariantScript":"\"Sales report\"","RuleProviderType":"Unknown"},{"Property":"BorderColor","Category":"Design","InvariantScript":"ColorFade(Self.Fill, -15%)","RuleProviderType":"Unknown"},{"Property":"DisabledBorderColor","Category":"Design","InvariantScript":"RGBA(166, 166, 166, 1)","RuleProviderType":"Unknown"},{"Property":"PressedBorderColor","Category":"Design","InvariantScript":"Self.Fill","RuleProviderType":"Unknown"},{"Property":"HoverBorderColor","Category":"Design","InvariantScript":"ColorFade(Self.BorderColor, 20%)","RuleProviderType":"Unknown"},{"Property":"BorderStyle","Category":"Design","InvariantScript":"BorderStyle.Solid","RuleProviderType":"Unknown"},{"Property":"FocusedBorderColor","Category":"Design","InvariantScript":"Self.BorderColor","RuleProviderType":"Unknown"},{"Property":"Color","Category":"Design","InvariantScript":"RGBA(255, 255, 255, 1)","RuleProviderType":"Unknown"},{"Property":"DisabledColor","Category":"Design","InvariantScript":"RGBA(166, 166, 166, 1)","RuleProviderType":"Unknown"},{"Property":"PressedColor","Category":"Design","InvariantScript":"Self.Fill","RuleProviderType":"Unknown"},{"Property":"HoverColor","Category":"Design","InvariantScript":"RGBA(255, 255, 255, 1)","RuleProviderType":"Unknown"},{"Property":"DisplayMode","Category":"Design","InvariantScript":"DisplayMode.Edit","RuleProviderType":"Unknown"},{"Property":"Fill","Category":"Design","InvariantScript":"RGBA(56, 96, 178, 1)","RuleProviderType":"Unknown"},{"Property":"DisabledFill","Category":"Design","InvariantScript":"RGBA(244, 244, 244, 1)","RuleProviderType":"Unknown"},{"Property":"PressedFill","Category":"Design","InvariantScript":"Self.Color","RuleProviderType":"Unknown"},{"Property":"HoverFill","Category":"Design","InvariantScript":"ColorFade(RGBA(56, 96, 178, 1), -20%)","RuleProviderType":"Unknown"},{"Property":"Font","Category":"Design","InvariantScript":"Font.'Open Sans'","RuleProviderType":"Unknown"},{"Property":"FontWeight","Category":"Design","InvariantScript":"FontWeight.Semibold","RuleProviderType":"Unknown"},{"Property":"Align","Category":"Design","InvariantScript":"Align.Center","RuleProviderType":"Unknown"},{"Property":"VerticalAlign","Category":"Design","InvariantScript":"VerticalAlign.Middle","RuleProviderType":"Unknown"},{"Property":"X","Category":"Design","InvariantScript":"905","RuleProviderType":"Unknown"},{"Property":"Y","Category":"Design","InvariantScript":"665","RuleProviderType":"Unknown"},{"Property":"Width","Category":"Design","InvariantScript":"182","RuleProviderType":"Unknown"},{"Property":"Height","Category":"Design","InvariantScript":"63","RuleProviderType":"Unknown"},{"Property":"ZIndex","Category":"Design","InvariantScript":"5","RuleProviderType":"Unknown"},{"Property":"RadiusTopLeft","Category":"Design","InvariantScript":"10","RuleProviderType":"Unknown"},{"Property":"RadiusTopRight","Category":"Design","InvariantScript":"10","RuleProviderType":"Unknown"},{"Property":"RadiusBottomLeft","Category":"Design","InvariantScript":"10","RuleProviderType":"Unknown"},{"Property":"RadiusBottomRight","Category":"Design","InvariantScript":"10","RuleProviderType":"Unknown"},{"Property":"BorderThickness","Category":"Design","InvariantScript":"2","RuleProviderType":"Unknown"},{"Property":"FocusedBorderThickness","Category":"Design","InvariantScript":"4","RuleProviderType":"Unknown"},{"Property":"Size","Category":"Design","InvariantScript":"15","RuleProviderType":"Unknown"},{"Property":"Italic","Category":"Design","InvariantScript":"false","RuleProviderType":"Unknown"},{"Property":"Underline","Category":"Design","InvariantScript":"false","RuleProviderType":"Unknown"},{"Property":"Strikethrough","Category":"Design","InvariantScript":"false","RuleProviderType":"Unknown"},{"Property":"OnSelect","Category":"Behavior","InvariantScript":"Navigate(Sales, ScreenTransition.Fade)","RuleProviderType":"Unknown"}],"ControlPropertyState":[{"InvariantPropertyName":"Text","AutoRuleBindingEnabled":false,"AutoRuleBindingString":"\"Button\"","NameMapSourceSchema":"?","IsLockable":false,"AFDDataSourceName":""},"BorderColor","DisabledBorderColor","PressedBorderColor","HoverBorderColor","BorderStyle","FocusedBorderColor","Color","DisabledColor","PressedColor","HoverColor","DisplayMode","Fill","DisabledFill","PressedFill","HoverFill","Font","FontWeight","Align","VerticalAlign","X","Y","Width","Height","ZIndex","RadiusTopLeft","RadiusTopRight","RadiusBottomLeft","RadiusBottomRight","BorderThickness","FocusedBorderThickness","Size","Italic","Underline","Strikethrough",{"InvariantPropertyName":"OnSelect","AutoRuleBindingEnabled":false,"AutoRuleBindingString":"false","NameMapSourceSchema":"?","IsLockable":false,"AFDDataSourceName":""}],"IsLocked":false,"ControlUniqueId":"25","Children":[]}]}}